crosspoint.v
module CROSSPOINT (
    input data_in,
    input cfg_in,
    output data_out
);

    assign data_out = data_in & cfg_in;
    
endmodule

SR.v
module SR #(
    parameter LEN=8
)(
    input CLK,
    input CFG,
    output reg [LEN-1:0] FF_CHAIN
);

// Shift left whenever a posedge occurs
always @(posedge CLK) begin
    FF_CHAIN    <= FF_CHAIN << 1;
    FF_CHAIN[0] <= CFG;
end

endmodule

PAL.v
module PAL #(
    parameter N = 8, // Number of Inputs
    parameter M = 8, // NUmber of outputs
    parameter P = 8 // Number of intermediate stages
)(
    input CLK,
    input CFG,
    input [N-1:0] INPUT_VARS,
    output [M-1:0] OUTPUT_VALS
);

    parameter SR_LEN = $signed((2*N * P) + P*M);

    // Configuration chain
    wire [SR_LEN-1:0] FF_CHAIN;

    // ---
    // FF_CHAIN
    //
    // <MSB> [ OR | ... | OR | OR | AND | ... | AND | AND | AND-INV | ... | AND-INV | AND-INV ] <LSB>
    //
    // When bit at INV is 1 then it is inverted!
    // ---
    // Indices for configuration chain
    parameter FF_CHAIN_OR_BASE_INDEX = $signed(2 * (N*P)); // the fully poopulated crossbar between N and P needs to be considered; *2 because of inverted & non-inverted inputs

    wire [FF_CHAIN_OR_BASE_INDEX-1:0] FF_CHAIN_AND;
    wire [SR_LEN-FF_CHAIN_OR_BASE_INDEX-1:0] FF_CHAIN_OR;

    assign FF_CHAIN_AND = FF_CHAIN[FF_CHAIN_OR_BASE_INDEX-1:0];
    assign FF_CHAIN_OR = FF_CHAIN[SR_LEN-1:FF_CHAIN_OR_BASE_INDEX];

    // Shift register (stores the configuration)
    SR #(
        .LEN(SR_LEN)
    ) sr (
        .CLK(CLK),
        .CFG(CFG),
        .FF_CHAIN(FF_CHAIN)
    );

    // NOT gates
    // redo this!
    wire [2*N-1:0] INPUT_VARS_N;
    wire [P-1:0] INTERM_VARS;

    // 
    //wire [P-1:0] and_cols[2*N-1:0];
    //wire [M-1:0] or_rows[P-1:0];
    wire [2*N-1:0] and_cols[P-1:0];
    wire [P-1:0] or_rows[M-1:0];
    wire test_lol;
    assign test_lol = CLK;


    // Iterators (running variables)
    genvar i;
    genvar p;
    genvar n;
    genvar m;
    // ---

    // n=0: 0&1
    // n=1: 2&3
    // n=2: 4&5
    // n=3: 6&7
    for (n = 0; n < N; n = n + 1) begin
        assign INPUT_VARS_N[2*n] = INPUT_VARS[n]; // even: keep
        assign INPUT_VARS_N[2*n+1] = ~INPUT_VARS[n]; // odd: invert
    end
    // ---

    // AND matrix
    generate
    for (p = 0; p < P; p = p + 1) begin : AND_GEN_LOOP_OUTER
        for (n = 0; n < $signed(2*N); n = n + 1 ) begin : AND_GEN_LOOP_INNER
            //assign INTERM_VARS[p] = INTERM_VARS[p] ^ (FF_CHAIN[FF_CHAIN_AND_BASE_INDEX + p + n*P] ^ INPUT_VARS[n]);
            //assign and_cols[p][n] = INPUT_VARS[n] ^ FF_CHAIN[$signed(FF_CHAIN_AND_BASE_INDEX + p + n*P)];
            CROSSPOINT cp (.data_in(INPUT_VARS_N[n]), .cfg_in(FF_CHAIN_AND[$signed(p + n*P)]), .data_out(and_cols[p][n]));
        end

        // Assign intermediate variables
        assign INTERM_VARS[p] = &and_cols[p]; // AND reduction
    end
    endgenerate
    
    // ---

    // OR matrix
    generate
    for (m = 0; m < M; m = m + 1) begin : OR_GEN_LOOP_OUTER
        for (p = 0; p < P; p = p + 1) begin : OR_GEN_LOOP_INNER
            //assign OUTPUT_VALS[m] = OUTPUT_VALS[m] | (FF_CHAIN[FF_CHAIN_OR_BASE_INDEX + p + m*P] ^ INTERM_VARS[p]);
            //assign or_rows[m][p] = INTERM_VARS[p] ^ FF_CHAIN[$signed(FF_CHAIN_OR_BASE_INDEX + p + m*P)];
            CROSSPOINT cp (.cfg_in(FF_CHAIN_OR[$signed(p + m*P)]), .data_in(INTERM_VARS[p]), .data_out(or_rows[m][p]));
        end

        // Assign to outputs
        assign OUTPUT_VALS[m] = |or_rows[m]; // OR reduction
    end
    endgenerate
    // ---
    
endmodule

testbench.v
module pal_tb ();

// configure these
parameter NUM_INPUTS = 4;
parameter NUM_OUPUTS = 3;
parameter NUM_INTERM_STAGES = 3;
// ---

reg clk_en_tb;
reg clk_tb;
wire clk_pal_tb;

assign clk_pal_tb = clk_tb ^ clk_en_tb;

reg config_tb;
reg [NUM_INPUTS-1:0] inputs_tb;
wire [NUM_OUPUTS-1:0] outputs_tb;

// UUT
PAL #(
    .N(NUM_INPUTS),
    .M(NUM_OUPUTS),
    .P(NUM_INTERM_STAGES)
) uut (
    .CLK(clk_pal_tb),
    .CFG(config_tb),
    .INPUT_VARS(inputs_tb),
    .OUTPUT_VALS(outputs_tb)
);

// Clock source
initial begin
    clk_tb=0;
    forever #10 clk_tb=~clk_tb;
end

/*initial begin
    // hehe...
    forever #10 config_tb = clk_tb;
end*/

initial begin
    // hehe...
   //forever #10 inputs_tb = {~clk_tb,clk_tb,~clk_tb,clk_tb,~clk_tb,clk_tb,~clk_tb,clk_tb};
   inputs_tb = 8'b0000_1111;
   forever #10 inputs_tb = ~inputs_tb;
end

// Testcase
initial begin
    $dumpfile("SIM.vcd");
    $dumpvars(0, pal_tb);

    config_tb = 1'b1;

    clk_en_tb = 1'b1;

    // INPUTS
    //inputs_tb = 8'b1010_1010;

    #1000

    clk_en_tb = 1'b0;

    #4000

    $finish;
end
    
endmodule

SIM.vcd
$date
	Mon Jan 22 20:52:49 2024
$end
$version
	Icarus Verilog
$end
$timescale
	1s
$end
$scope module pal_tb $end
$var wire 1 ! clk_pal_tb $end
$var wire 3 " outputs_tb [2:0] $end
$var parameter 32 # NUM_INPUTS $end
$var parameter 32 $ NUM_INTERM_STAGES $end
$var parameter 32 % NUM_OUPUTS $end
$var reg 1 & clk_en_tb $end
$var reg 1 ' clk_tb $end
$var reg 1 ( config_tb $end
$var reg 4 ) inputs_tb [3:0] $end
$scope module uut $end
$var wire 1 ( CFG $end
$var wire 1 ! CLK $end
$var wire 4 * INPUT_VARS [3:0] $end
$var wire 1 + test_lol $end
$var wire 3 , OUTPUT_VALS [2:0] $end
$var wire 3 - INTERM_VARS [2:0] $end
$var wire 8 . INPUT_VARS_N [7:0] $end
$var wire 9 / FF_CHAIN_OR [8:0] $end
$var wire 24 0 FF_CHAIN_AND [23:0] $end
$var wire 33 1 FF_CHAIN [32:0] $end
$var parameter 32 2 FF_CHAIN_OR_BASE_INDEX $end
$var parameter 32 3 M $end
$var parameter 32 4 N $end
$var parameter 32 5 P $end
$var parameter 32 6 SR_LEN $end
$scope begin AND_GEN_LOOP_OUTER[0] $end
$var parameter 2 7 p $end
$scope begin AND_GEN_LOOP_INNER[0] $end
$var parameter 2 8 n $end
$scope module cp $end
$var wire 1 9 cfg_in $end
$var wire 1 : data_in $end
$var wire 1 ; data_out $end
$upscope $end
$upscope $end
$scope begin AND_GEN_LOOP_INNER[1] $end
$var parameter 2 < n $end
$scope module cp $end
$var wire 1 = cfg_in $end
$var wire 1 > data_in $end
$var wire 1 ? data_out $end
$upscope $end
$upscope $end
$scope begin AND_GEN_LOOP_INNER[2] $end
$var parameter 3 @ n $end
$scope module cp $end
$var wire 1 A cfg_in $end
$var wire 1 B data_in $end
$var wire 1 C data_out $end
$upscope $end
$upscope $end
$scope begin AND_GEN_LOOP_INNER[3] $end
$var parameter 3 D n $end
$scope module cp $end
$var wire 1 E cfg_in $end
$var wire 1 F data_in $end
$var wire 1 G data_out $end
$upscope $end
$upscope $end
$scope begin AND_GEN_LOOP_INNER[4] $end
$var parameter 4 H n $end
$scope module cp $end
$var wire 1 I cfg_in $end
$var wire 1 J data_in $end
$var wire 1 K data_out $end
$upscope $end
$upscope $end
$scope begin AND_GEN_LOOP_INNER[5] $end
$var parameter 4 L n $end
$scope module cp $end
$var wire 1 M cfg_in $end
$var wire 1 N data_in $end
$var wire 1 O data_out $end
$upscope $end
$upscope $end
$scope begin AND_GEN_LOOP_INNER[6] $end
$var parameter 4 P n $end
$scope module cp $end
$var wire 1 Q cfg_in $end
$var wire 1 R data_in $end
$var wire 1 S data_out $end
$upscope $end
$upscope $end
$scope begin AND_GEN_LOOP_INNER[7] $end
$var parameter 4 T n $end
$scope module cp $end
$var wire 1 U cfg_in $end
$var wire 1 V data_in $end
$var wire 1 W data_out $end
$upscope $end
$upscope $end
$upscope $end
$scope begin AND_GEN_LOOP_OUTER[1] $end
$var parameter 2 X p $end
$scope begin AND_GEN_LOOP_INNER[0] $end
$var parameter 2 Y n $end
$scope module cp $end
$var wire 1 Z cfg_in $end
$var wire 1 [ data_in $end
$var wire 1 \ data_out $end
$upscope $end
$upscope $end
$scope begin AND_GEN_LOOP_INNER[1] $end
$var parameter 2 ] n $end
$scope module cp $end
$var wire 1 ^ cfg_in $end
$var wire 1 _ data_in $end
$var wire 1 ` data_out $end
$upscope $end
$upscope $end
$scope begin AND_GEN_LOOP_INNER[2] $end
$var parameter 3 a n $end
$scope module cp $end
$var wire 1 b cfg_in $end
$var wire 1 c data_in $end
$var wire 1 d data_out $end
$upscope $end
$upscope $end
$scope begin AND_GEN_LOOP_INNER[3] $end
$var parameter 3 e n $end
$scope module cp $end
$var wire 1 f cfg_in $end
$var wire 1 g data_in $end
$var wire 1 h data_out $end
$upscope $end
$upscope $end
$scope begin AND_GEN_LOOP_INNER[4] $end
$var parameter 4 i n $end
$scope module cp $end
$var wire 1 j cfg_in $end
$var wire 1 k data_in $end
$var wire 1 l data_out $end
$upscope $end
$upscope $end
$scope begin AND_GEN_LOOP_INNER[5] $end
$var parameter 4 m n $end
$scope module cp $end
$var wire 1 n cfg_in $end
$var wire 1 o data_in $end
$var wire 1 p data_out $end
$upscope $end
$upscope $end
$scope begin AND_GEN_LOOP_INNER[6] $end
$var parameter 4 q n $end
$scope module cp $end
$var wire 1 r cfg_in $end
$var wire 1 s data_in $end
$var wire 1 t data_out $end
$upscope $end
$upscope $end
$scope begin AND_GEN_LOOP_INNER[7] $end
$var parameter 4 u n $end
$scope module cp $end
$var wire 1 v cfg_in $end
$var wire 1 w data_in $end
$var wire 1 x data_out $end
$upscope $end
$upscope $end
$upscope $end
$scope begin AND_GEN_LOOP_OUTER[2] $end
$var parameter 3 y p $end
$scope begin AND_GEN_LOOP_INNER[0] $end
$var parameter 2 z n $end
$scope module cp $end
$var wire 1 { cfg_in $end
$var wire 1 | data_in $end
$var wire 1 } data_out $end
$upscope $end
$upscope $end
$scope begin AND_GEN_LOOP_INNER[1] $end
$var parameter 2 ~ n $end
$scope module cp $end
$var wire 1 !" cfg_in $end
$var wire 1 "" data_in $end
$var wire 1 #" data_out $end
$upscope $end
$upscope $end
$scope begin AND_GEN_LOOP_INNER[2] $end
$var parameter 3 $" n $end
$scope module cp $end
$var wire 1 %" cfg_in $end
$var wire 1 &" data_in $end
$var wire 1 '" data_out $end
$upscope $end
$upscope $end
$scope begin AND_GEN_LOOP_INNER[3] $end
$var parameter 3 (" n $end
$scope module cp $end
$var wire 1 )" cfg_in $end
$var wire 1 *" data_in $end
$var wire 1 +" data_out $end
$upscope $end
$upscope $end
$scope begin AND_GEN_LOOP_INNER[4] $end
$var parameter 4 ," n $end
$scope module cp $end
$var wire 1 -" cfg_in $end
$var wire 1 ." data_in $end
$var wire 1 /" data_out $end
$upscope $end
$upscope $end
$scope begin AND_GEN_LOOP_INNER[5] $end
$var parameter 4 0" n $end
$scope module cp $end
$var wire 1 1" cfg_in $end
$var wire 1 2" data_in $end
$var wire 1 3" data_out $end
$upscope $end
$upscope $end
$scope begin AND_GEN_LOOP_INNER[6] $end
$var parameter 4 4" n $end
$scope module cp $end
$var wire 1 5" cfg_in $end
$var wire 1 6" data_in $end
$var wire 1 7" data_out $end
$upscope $end
$upscope $end
$scope begin AND_GEN_LOOP_INNER[7] $end
$var parameter 4 8" n $end
$scope module cp $end
$var wire 1 9" cfg_in $end
$var wire 1 :" data_in $end
$var wire 1 ;" data_out $end
$upscope $end
$upscope $end
$upscope $end
$scope begin OR_GEN_LOOP_OUTER[0] $end
$var parameter 2 <" m $end
$scope begin OR_GEN_LOOP_INNER[0] $end
$var parameter 2 =" p $end
$scope module cp $end
$var wire 1 >" cfg_in $end
$var wire 1 ?" data_in $end
$var wire 1 @" data_out $end
$upscope $end
$upscope $end
$scope begin OR_GEN_LOOP_INNER[1] $end
$var parameter 2 A" p $end
$scope module cp $end
$var wire 1 B" cfg_in $end
$var wire 1 C" data_in $end
$var wire 1 D" data_out $end
$upscope $end
$upscope $end
$scope begin OR_GEN_LOOP_INNER[2] $end
$var parameter 3 E" p $end
$scope module cp $end
$var wire 1 F" cfg_in $end
$var wire 1 G" data_in $end
$var wire 1 H" data_out $end
$upscope $end
$upscope $end
$upscope $end
$scope begin OR_GEN_LOOP_OUTER[1] $end
$var parameter 2 I" m $end
$scope begin OR_GEN_LOOP_INNER[0] $end
$var parameter 2 J" p $end
$scope module cp $end
$var wire 1 K" cfg_in $end
$var wire 1 L" data_in $end
$var wire 1 M" data_out $end
$upscope $end
$upscope $end
$scope begin OR_GEN_LOOP_INNER[1] $end
$var parameter 2 N" p $end
$scope module cp $end
$var wire 1 O" cfg_in $end
$var wire 1 P" data_in $end
$var wire 1 Q" data_out $end
$upscope $end
$upscope $end
$scope begin OR_GEN_LOOP_INNER[2] $end
$var parameter 3 R" p $end
$scope module cp $end
$var wire 1 S" cfg_in $end
$var wire 1 T" data_in $end
$var wire 1 U" data_out $end
$upscope $end
$upscope $end
$upscope $end
$scope begin OR_GEN_LOOP_OUTER[2] $end
$var parameter 3 V" m $end
$scope begin OR_GEN_LOOP_INNER[0] $end
$var parameter 2 W" p $end
$scope module cp $end
$var wire 1 X" cfg_in $end
$var wire 1 Y" data_in $end
$var wire 1 Z" data_out $end
$upscope $end
$upscope $end
$scope begin OR_GEN_LOOP_INNER[1] $end
$var parameter 2 [" p $end
$scope module cp $end
$var wire 1 \" cfg_in $end
$var wire 1 ]" data_in $end
$var wire 1 ^" data_out $end
$upscope $end
$upscope $end
$scope begin OR_GEN_LOOP_INNER[2] $end
$var parameter 3 _" p $end
$scope module cp $end
$var wire 1 `" cfg_in $end
$var wire 1 a" data_in $end
$var wire 1 b" data_out $end
$upscope $end
$upscope $end
$upscope $end
$scope begin genblk1[0] $end
$var parameter 2 c" n $end
$upscope $end
$scope begin genblk1[1] $end
$var parameter 2 d" n $end
$upscope $end
$scope begin genblk1[2] $end
$var parameter 3 e" n $end
$upscope $end
$scope begin genblk1[3] $end
$var parameter 3 f" n $end
$upscope $end
$scope module sr $end
$var wire 1 ( CFG $end
$var wire 1 ! CLK $end
$var parameter 32 g" LEN $end
$var reg 33 h" FF_CHAIN [32:0] $end
$upscope $end
$upscope $end
$upscope $end
$enddefinitions $end
$comment Show the parameter values. $end
$dumpall
b100001 g"
b11 f"
b10 e"
b1 d"
b0 c"
b10 _"
b1 ["
b0 W"
b10 V"
b10 R"
b1 N"
b0 J"
b1 I"
b10 E"
b1 A"
b0 ="
b0 <"
b111 8"
b110 4"
b101 0"
b100 ,"
b11 ("
b10 $"
b1 ~
b0 z
b10 y
b111 u
b110 q
b101 m
b100 i
b11 e
b10 a
b1 ]
b0 Y
b1 X
b111 T
b110 P
b101 L
b100 H
b11 D
b10 @
b1 <
b0 8
b0 7
b100001 6
b11 5
b100 4
b11 3
b11000 2
b11 %
b11 $
b100 #
$end
#0
$dumpvars
bx1 h"
0b"
0a"
x`"
0^"
0]"
x\"
0Z"
0Y"
xX"
0U"
0T"
xS"
0Q"
0P"
xO"
0M"
0L"
xK"
0H"
0G"
xF"
0D"
0C"
xB"
0@"
0?"
x>"
0;"
0:"
x9"
x7"
16"
x5"
03"
02"
x1"
x/"
1."
x-"
0+"
0*"
x)"
x'"
1&"
x%"
0#"
0""
x!"
x}
1|
x{
0x
0w
xv
xt
1s
xr
0p
0o
xn
xl
1k
xj
0h
0g
xf
xd
1c
xb
0`
0_
x^
x\
1[
xZ
0W
0V
xU
xS
1R
xQ
0O
0N
xM
xK
1J
xI
0G
0F
xE
xC
1B
xA
0?
0>
x=
1;
1:
19
bx1 1
bx1 0
bx /
b1010101 .
b0 -
b0 ,
1+
b1111 *
b1111 )
1(
0'
1&
b0 "
1!
$end
#10
x?
x`
x#"
xG
xh
x+"
xO
xp
x3"
xW
xx
x;"
0;
0\
0}
1>
1_
1""
0C
0d
0'"
1F
1g
1*"
0K
0l
0/"
1N
1o
12"
0S
0t
07"
1V
1w
1:"
0:
0[
0|
0B
0c
0&"
0J
0k
0."
0R
0s
06"
b10101010 .
0+
0!
b0 )
b0 *
1'
#20
1Z
bx11 0
bx11 1
bx11 h"
0?
0`
0#"
0G
0h
0+"
0O
0p
03"
0W
0x
0;"
1;
1\
b0 -
x}
0>
0_
0""
xC
xd
x'"
0F
0g
0*"
xK
xl
x/"
0N
0o
02"
xS
xt
x7"
0V
0w
0:"
1:
1[
1|
1B
1c
1&"
1J
1k
1."
1R
1s
16"
b1010101 .
1+
1!
b1111 )
b1111 *
0'
#30
x?
x`
x#"
xG
xh
x+"
xO
xp
x3"
xW
xx
x;"
0;
0\
0}
1>
1_
1""
0C
0d
0'"
1F
1g
1*"
0K
0l
0/"
1N
1o
12"
0S
0t
07"
1V
1w
1:"
0:
0[
0|
0B
0c
0&"
0J
0k
0."
0R
0s
06"
b10101010 .
0+
0!
b0 )
b0 *
1'
#40
1{
bx111 0
bx111 1
bx111 h"
0?
0`
0#"
0G
0h
0+"
0O
0p
03"
0W
0x
0;"
1;
1\
b0 -
1}
0>
0_
0""
xC
xd
x'"
0F
0g
0*"
xK
xl
x/"
0N
0o
02"
xS
xt
x7"
0V
0w
0:"
1:
1[
1|
1B
1c
1&"
1J
1k
1."
1R
1s
16"
b1010101 .
1+
1!
b1111 )
b1111 *
0'
#50
x?
x`
x#"
xG
xh
x+"
xO
xp
x3"
xW
xx
x;"
0;
0\
0}
1>
1_
1""
0C
0d
0'"
1F
1g
1*"
0K
0l
0/"
1N
1o
12"
0S
0t
07"
1V
1w
1:"
0:
0[
0|
0B
0c
0&"
0J
0k
0."
0R
0s
06"
b10101010 .
0+
0!
b0 )
b0 *
1'
#60
1=
bx1111 0
bx1111 1
bx1111 h"
0?
0`
0#"
0G
0h
0+"
0O
0p
03"
0W
0x
0;"
1;
1\
b0 -
1}
0>
0_
0""
xC
xd
x'"
0F
0g
0*"
xK
xl
x/"
0N
0o
02"
xS
xt
x7"
0V
0w
0:"
1:
1[
1|
1B
1c
1&"
1J
1k
1."
1R
1s
16"
b1010101 .
1+
1!
b1111 )
b1111 *
0'
#70
1?
x`
x#"
xG
xh
x+"
xO
xp
x3"
xW
xx
x;"
0;
0\
0}
1>
1_
1""
0C
0d
0'"
1F
1g
1*"
0K
0l
0/"
1N
1o
12"
0S
0t
07"
1V
1w
1:"
0:
0[
0|
0B
0c
0&"
0J
0k
0."
0R
0s
06"
b10101010 .
0+
0!
b0 )
b0 *
1'
#80
1^
bx11111 0
bx11111 1
bx11111 h"
0?
0`
0#"
0G
0h
0+"
0O
0p
03"
0W
0x
0;"
1;
1\
b0 -
1}
0>
0_
0""
xC
xd
x'"
0F
0g
0*"
xK
xl
x/"
0N
0o
02"
xS
xt
x7"
0V
0w
0:"
1:
1[
1|
1B
1c
1&"
1J
1k
1."
1R
1s
16"
b1010101 .
1+
1!
b1111 )
b1111 *
0'
#90
1?
1`
x#"
xG
xh
x+"
xO
xp
x3"
xW
xx
x;"
0;
0\
0}
1>
1_
1""
0C
0d
0'"
1F
1g
1*"
0K
0l
0/"
1N
1o
12"
0S
0t
07"
1V
1w
1:"
0:
0[
0|
0B
0c
0&"
0J
0k
0."
0R
0s
06"
b10101010 .
0+
0!
b0 )
b0 *
1'
#100
1!"
bx111111 0
bx111111 1
bx111111 h"
0?
0`
0#"
0G
0h
0+"
0O
0p
03"
0W
0x
0;"
1;
1\
b0 -
1}
0>
0_
0""
xC
xd
x'"
0F
0g
0*"
xK
xl
x/"
0N
0o
02"
xS
xt
x7"
0V
0w
0:"
1:
1[
1|
1B
1c
1&"
1J
1k
1."
1R
1s
16"
b1010101 .
1+
1!
b1111 )
b1111 *
0'
#110
1?
1`
1#"
xG
xh
x+"
xO
xp
x3"
xW
xx
x;"
0;
0\
0}
1>
1_
1""
0C
0d
0'"
1F
1g
1*"
0K
0l
0/"
1N
1o
12"
0S
0t
07"
1V
1w
1:"
0:
0[
0|
0B
0c
0&"
0J
0k
0."
0R
0s
06"
b10101010 .
0+
0!
b0 )
b0 *
1'
#120
1A
bx1111111 0
bx1111111 1
bx1111111 h"
0?
0`
0#"
0G
0h
0+"
0O
0p
03"
0W
0x
0;"
1;
1\
b0 -
1}
0>
0_
0""
1C
xd
x'"
0F
0g
0*"
xK
xl
x/"
0N
0o
02"
xS
xt
x7"
0V
0w
0:"
1:
1[
1|
1B
1c
1&"
1J
1k
1."
1R
1s
16"
b1010101 .
1+
1!
b1111 )
b1111 *
0'
#130
1?
1`
1#"
xG
xh
x+"
xO
xp
x3"
xW
xx
x;"
0;
0\
0}
1>
1_
1""
0C
0d
0'"
1F
1g
1*"
0K
0l
0/"
1N
1o
12"
0S
0t
07"
1V
1w
1:"
0:
0[
0|
0B
0c
0&"
0J
0k
0."
0R
0s
06"
b10101010 .
0+
0!
b0 )
b0 *
1'
#140
1b
bx11111111 0
bx11111111 1
bx11111111 h"
0?
0`
0#"
0G
0h
0+"
0O
0p
03"
0W
0x
0;"
1;
1\
b0 -
1}
0>
0_
0""
1C
1d
x'"
0F
0g
0*"
xK
xl
x/"
0N
0o
02"
xS
xt
x7"
0V
0w
0:"
1:
1[
1|
1B
1c
1&"
1J
1k
1."
1R
1s
16"
b1010101 .
1+
1!
b1111 )
b1111 *
0'
#150
1?
1`
1#"
xG
xh
x+"
xO
xp
x3"
xW
xx
x;"
0;
0\
0}
1>
1_
1""
0C
0d
0'"
1F
1g
1*"
0K
0l
0/"
1N
1o
12"
0S
0t
07"
1V
1w
1:"
0:
0[
0|
0B
0c
0&"
0J
0k
0."
0R
0s
06"
b10101010 .
0+
0!
b0 )
b0 *
1'
#160
1%"
bx111111111 0
bx111111111 1
bx111111111 h"
0?
0`
0#"
0G
0h
0+"
0O
0p
03"
0W
0x
0;"
1;
1\
b0 -
1}
0>
0_
0""
1C
1d
1'"
0F
0g
0*"
xK
xl
x/"
0N
0o
02"
xS
xt
x7"
0V
0w
0:"
1:
1[
1|
1B
1c
1&"
1J
1k
1."
1R
1s
16"
b1010101 .
1+
1!
b1111 )
b1111 *
0'
#170
1?
1`
1#"
xG
xh
x+"
xO
xp
x3"
xW
xx
x;"
0;
0\
0}
1>
1_
1""
0C
0d
0'"
1F
1g
1*"
0K
0l
0/"
1N
1o
12"
0S
0t
07"
1V
1w
1:"
0:
0[
0|
0B
0c
0&"
0J
0k
0."
0R
0s
06"
b10101010 .
0+
0!
b0 )
b0 *
1'
#180
1E
bx1111111111 0
bx1111111111 1
bx1111111111 h"
0?
0`
0#"
0G
0h
0+"
0O
0p
03"
0W
0x
0;"
1;
1\
b0 -
1}
0>
0_
0""
1C
1d
1'"
0F
0g
0*"
xK
xl
x/"
0N
0o
02"
xS
xt
x7"
0V
0w
0:"
1:
1[
1|
1B
1c
1&"
1J
1k
1."
1R
1s
16"
b1010101 .
1+
1!
b1111 )
b1111 *
0'
#190
1?
1`
1#"
1G
xh
x+"
xO
xp
x3"
xW
xx
x;"
0;
0\
0}
1>
1_
1""
0C
0d
0'"
1F
1g
1*"
0K
0l
0/"
1N
1o
12"
0S
0t
07"
1V
1w
1:"
0:
0[
0|
0B
0c
0&"
0J
0k
0."
0R
0s
06"
b10101010 .
0+
0!
b0 )
b0 *
1'
#200
1f
bx11111111111 0
bx11111111111 1
bx11111111111 h"
0?
0`
0#"
0G
0h
0+"
0O
0p
03"
0W
0x
0;"
1;
1\
b0 -
1}
0>
0_
0""
1C
1d
1'"
0F
0g
0*"
xK
xl
x/"
0N
0o
02"
xS
xt
x7"
0V
0w
0:"
1:
1[
1|
1B
1c
1&"
1J
1k
1."
1R
1s
16"
b1010101 .
1+
1!
b1111 )
b1111 *
0'
#210
1?
1`
1#"
1G
1h
x+"
xO
xp
x3"
xW
xx
x;"
0;
0\
0}
1>
1_
1""
0C
0d
0'"
1F
1g
1*"
0K
0l
0/"
1N
1o
12"
0S
0t
07"
1V
1w
1:"
0:
0[
0|
0B
0c
0&"
0J
0k
0."
0R
0s
06"
b10101010 .
0+
0!
b0 )
b0 *
1'
#220
1)"
bx111111111111 0
bx111111111111 1
bx111111111111 h"
0?
0`
0#"
0G
0h
0+"
0O
0p
03"
0W
0x
0;"
1;
1\
b0 -
1}
0>
0_
0""
1C
1d
1'"
0F
0g
0*"
xK
xl
x/"
0N
0o
02"
xS
xt
x7"
0V
0w
0:"
1:
1[
1|
1B
1c
1&"
1J
1k
1."
1R
1s
16"
b1010101 .
1+
1!
b1111 )
b1111 *
0'
#230
1?
1`
1#"
1G
1h
1+"
xO
xp
x3"
xW
xx
x;"
0;
0\
0}
1>
1_
1""
0C
0d
0'"
1F
1g
1*"
0K
0l
0/"
1N
1o
12"
0S
0t
07"
1V
1w
1:"
0:
0[
0|
0B
0c
0&"
0J
0k
0."
0R
0s
06"
b10101010 .
0+
0!
b0 )
b0 *
1'
#240
1I
bx1111111111111 0
bx1111111111111 1
bx1111111111111 h"
0?
0`
0#"
0G
0h
0+"
0O
0p
03"
0W
0x
0;"
1;
1\
b0 -
1}
0>
0_
0""
1C
1d
1'"
0F
0g
0*"
1K
xl
x/"
0N
0o
02"
xS
xt
x7"
0V
0w
0:"
1:
1[
1|
1B
1c
1&"
1J
1k
1."
1R
1s
16"
b1010101 .
1+
1!
b1111 )
b1111 *
0'
#250
1?
1`
1#"
1G
1h
1+"
xO
xp
x3"
xW
xx
x;"
0;
0\
0}
1>
1_
1""
0C
0d
0'"
1F
1g
1*"
0K
0l
0/"
1N
1o
12"
0S
0t
07"
1V
1w
1:"
0:
0[
0|
0B
0c
0&"
0J
0k
0."
0R
0s
06"
b10101010 .
0+
0!
b0 )
b0 *
1'
#260
1j
bx11111111111111 0
bx11111111111111 1
bx11111111111111 h"
0?
0`
0#"
0G
0h
0+"
0O
0p
03"
0W
0x
0;"
1;
1\
b0 -
1}
0>
0_
0""
1C
1d
1'"
0F
0g
0*"
1K
1l
x/"
0N
0o
02"
xS
xt
x7"
0V
0w
0:"
1:
1[
1|
1B
1c
1&"
1J
1k
1."
1R
1s
16"
b1010101 .
1+
1!
b1111 )
b1111 *
0'
#270
1?
1`
1#"
1G
1h
1+"
xO
xp
x3"
xW
xx
x;"
0;
0\
0}
1>
1_
1""
0C
0d
0'"
1F
1g
1*"
0K
0l
0/"
1N
1o
12"
0S
0t
07"
1V
1w
1:"
0:
0[
0|
0B
0c
0&"
0J
0k
0."
0R
0s
06"
b10101010 .
0+
0!
b0 )
b0 *
1'
#280
1-"
bx111111111111111 0
bx111111111111111 1
bx111111111111111 h"
0?
0`
0#"
0G
0h
0+"
0O
0p
03"
0W
0x
0;"
1;
1\
b0 -
1}
0>
0_
0""
1C
1d
1'"
0F
0g
0*"
1K
1l
1/"
0N
0o
02"
xS
xt
x7"
0V
0w
0:"
1:
1[
1|
1B
1c
1&"
1J
1k
1."
1R
1s
16"
b1010101 .
1+
1!
b1111 )
b1111 *
0'
#290
1?
1`
1#"
1G
1h
1+"
xO
xp
x3"
xW
xx
x;"
0;
0\
0}
1>
1_
1""
0C
0d
0'"
1F
1g
1*"
0K
0l
0/"
1N
1o
12"
0S
0t
07"
1V
1w
1:"
0:
0[
0|
0B
0c
0&"
0J
0k
0."
0R
0s
06"
b10101010 .
0+
0!
b0 )
b0 *
1'
#300
1M
bx1111111111111111 0
bx1111111111111111 1
bx1111111111111111 h"
0?
0`
0#"
0G
0h
0+"
0O
0p
03"
0W
0x
0;"
1;
1\
b0 -
1}
0>
0_
0""
1C
1d
1'"
0F
0g
0*"
1K
1l
1/"
0N
0o
02"
xS
xt
x7"
0V
0w
0:"
1:
1[
1|
1B
1c
1&"
1J
1k
1."
1R
1s
16"
b1010101 .
1+
1!
b1111 )
b1111 *
0'
#310
1?
1`
1#"
1G
1h
1+"
1O
xp
x3"
xW
xx
x;"
0;
0\
0}
1>
1_
1""
0C
0d
0'"
1F
1g
1*"
0K
0l
0/"
1N
1o
12"
0S
0t
07"
1V
1w
1:"
0:
0[
0|
0B
0c
0&"
0J
0k
0."
0R
0s
06"
b10101010 .
0+
0!
b0 )
b0 *
1'
#320
1n
bx11111111111111111 0
bx11111111111111111 1
bx11111111111111111 h"
0?
0`
0#"
0G
0h
0+"
0O
0p
03"
0W
0x
0;"
1;
1\
b0 -
1}
0>
0_
0""
1C
1d
1'"
0F
0g
0*"
1K
1l
1/"
0N
0o
02"
xS
xt
x7"
0V
0w
0:"
1:
1[
1|
1B
1c
1&"
1J
1k
1."
1R
1s
16"
b1010101 .
1+
1!
b1111 )
b1111 *
0'
#330
1?
1`
1#"
1G
1h
1+"
1O
1p
x3"
xW
xx
x;"
0;
0\
0}
1>
1_
1""
0C
0d
0'"
1F
1g
1*"
0K
0l
0/"
1N
1o
12"
0S
0t
07"
1V
1w
1:"
0:
0[
0|
0B
0c
0&"
0J
0k
0."
0R
0s
06"
b10101010 .
0+
0!
b0 )
b0 *
1'
#340
11"
bx111111111111111111 0
bx111111111111111111 1
bx111111111111111111 h"
0?
0`
0#"
0G
0h
0+"
0O
0p
03"
0W
0x
0;"
1;
1\
b0 -
1}
0>
0_
0""
1C
1d
1'"
0F
0g
0*"
1K
1l
1/"
0N
0o
02"
xS
xt
x7"
0V
0w
0:"
1:
1[
1|
1B
1c
1&"
1J
1k
1."
1R
1s
16"
b1010101 .
1+
1!
b1111 )
b1111 *
0'
